pycolarised/__init__.py
pycolarised-2.9.dist-info/METADATA
pycolarised-2.9.dist-info/WHEEL
pycolarised-2.9.dist-info/top_level.txt
pycolarised-2.9.dist-info/RECORD
