Metadata-Version: 2.1
Name: pycolarised
Version: 2.9
Summary: by johndayne
Author-email: <johndayne356@gmail.com>
License: Eclipse Public License 2.0
